{"link": "https://www.themoviedb.org/tv/62448?language=en", "title": "Wege \u00fcbers Land", "resume": "We don't have an overview translated in English. Help us expand our database by adding one.", "rate": 0, "genre": ["Drama"], "cast": ["Ursula Karusseit", "Christa Lehmann", "Erika Pelikowsky", "Armin Mueller-Stahl", "Erik S. Klein"], "character": ["Gertrud Habersaat", "die alte Habersaat", "die alte Le\u00dftorff", "J\u00fcrgen Le\u00dftorff", "Emil Kalluweit"], "site_data": "html Apps Forums Leaderboard Contribute API Support Discover Movies TV Shows Movies Popular Top Rated Upcoming Now Playing TV Shows Popular Top Rated On TV Airing Today People Popular People Can't find a movie or TV show? Login to create it. en Login Sign Up  ID: 62448   Expand Wege \u00fcbers Land   (1968) User Score Overview We don't have an overview translated in English. Help us expand our database by adding one. Discussions   Reviews Videos   Images   Changes Report Share Discussions General  0 Content Issues  0 Images Backdrops  4 Posters  1 Videos Trailers  0 Teasers  0 Clips  0 Featurettes  0 Opening Credits  0 Top Billed Cast Ursula Karusseit Gertrud Habersaat Christa Lehmann die alte Habersaat Erika Pelikowsky die alte Le\u00dftorff Armin Mueller-Stahl J\u00fcrgen Le\u00dftorff Erik S. Klein Emil Kalluweit Full Cast & Crew Last Season Season 1 1968 | 5 Episodes Season 1 of Wege \u00fcbers Land premiered on September 22, 1968. View All Seasons Social Reviews  0 Discussions  0 Media Most Popular Videos  0 Backdrops  4 Posters  1 Recommendations We don't have enough data to suggest any TV shows based on Wege \u00fcbers Land. You can help by rating TV shows you've seen. Facts Status  Ended Networks - Certification 6 Meaning Can be aired at any time. Type  Scripted Original Language  German Runtime  69m, 86m, 112m, 121m, 56m Homepage   http://www.deutscher-fernsehfunk.de/ Genres Drama Keywords No keywords have been added. Content Score 79 Pump it up! We're close now. Top Contributors x 80 xPR S 6 Samara 2 Elizabeth Jennings  View Edit History Popularity Trend  Login to edit  URL By  signing up  for an account on TMDb, you can post directly to Twitter and Facebook. You need to be logged in to continue. Click  here  to login or  here  to sign up.    page_wrap opened in html_head  Join the Community The Basics About TMDb Contact Us Support Forums API Blog Get Involved  Contribution Bible 3rd Party Applications Add New Movie Add New TV Show Community Guidelines Leaderboard Forums Twitter Facebook Legal Terms of Use Privacy Policy Login Sign Up"}