{"title": "Lethal Weapon", "link": "https://trakt.tv/shows/lethal-weapon", "genre": ["Drama", "Crime", "Action", "Adventure"], "rate": 82, "resume": "Grief-stricken ex-Navy SEAL-turned-detective Martin Riggs moves to California to \u201cstart over\u201d at the LAPD. He\u2019s paired up with Roger Murtaugh, who\u2019s just coming back to the job after a near-fatal heart attack. Riggs\u2019 penchant for diving headfirst into the line of fire immediately clashes with Murtaugh\u2019s prudent, by-the-book technique.", "cast": ["Clayne Crawford", "Damon Wayans", "Jordana Brewster", "Kevin Rahm", "Keesha Sharp", "Michelle Mitchenor", "Johnathan Fernandez", "Dante Brown", "Chandler Kinney"], "character": ["Martin Riggs", "Roger Murtaugh", "Maureen Cahill", "Brooks Avery", "Trish Murtaugh", "Sonya Bailey", "Scorsese", "Roger Murtaugh, Jr.", "Riana Murtaugh"]}