{"link": "https://www.themoviedb.org/tv/1439?language=en", "title": "Here's Lucy", "resume": "Here's Lucy is Lucille Ball's third network television sitcom. It ran on CBS from 1968 to 1974.", "rate": 71, "genre": ["Comedy"], "cast": ["Lucille Ball", "Gale Gordon", "Lucie Arnaz"], "character": ["Lucy Carter"], "site_data": "html Apps Forums Leaderboard Contribute API Support Discover Movies TV Shows Movies Popular Top Rated Upcoming Now Playing TV Shows Popular Top Rated On TV Airing Today People Popular People Can't find a movie or TV show? Login to create it. en Login Sign Up  ID: 1439   Expand Here's Lucy   (1968) User Score Overview Here's Lucy is Lucille Ball's third network television sitcom. It ran on CBS from 1968 to 1974. Featured Crew Lucille Ball Creator Discussions   Reviews Videos   Images   Changes Report Share Discussions General  0 Content Issues  0 Images Backdrops  1 Posters  1 Videos Trailers  0 Teasers  0 Clips  0 Featurettes  0 Opening Credits  0 Top Billed Cast Lucille Ball Lucy Carter Gale Gordon Lucie Arnaz Full Cast & Crew Last Season Season 6 1973 | 24 Episodes Season 6 of Here's Lucy premiered on September 10, 1973. View All Seasons Social Reviews  0 Discussions  0 Media Most Popular Videos  0 Backdrops  1 Posters  1 Recommendations   1972-09-17 Anna and the King 5.0    1972-10-19 Colditz 9.0    1965-09-01 Gidget 5.2    1967-09-10 Gentle Ben 5.0    1954-10-15 The Adventures of Rin Tin Tin 6.5    1970-09-17 The Flip Wilson Show 3.7    1979-09-30 To the Manor Born 7.1    1968-09-28 The Ghost & Mrs. Muir 6.7  Facts Status  Ended Network Certification  - Type  Scripted Original Language  English Runtime  30m, 25m Homepage  - Genres Comedy Keywords employment agency los angeles single mother sitcom Content Score 64 We're so close, yet so far. Top Contributors 8 Banana 1 DarkMan 1 Axholio  View Edit History Popularity Trend  Login to edit  URL By  signing up  for an account on TMDb, you can post directly to Twitter and Facebook. You need to be logged in to continue. Click  here  to login or  here  to sign up.    page_wrap opened in html_head  Join the Community The Basics About TMDb Contact Us Support Forums API Blog Get Involved  Contribution Bible 3rd Party Applications Add New Movie Add New TV Show Community Guidelines Leaderboard Forums Twitter Facebook Legal Terms of Use Privacy Policy Login Sign Up"}