{"link": "https://www.themoviedb.org/tv/27212?language=en", "title": "The Bullwinkle Show", "resume": "We don't have an overview translated in English. Help us expand our database by adding one.", "rate": 74, "genre": ["Animation"], "cast": ["William Conrad", "Edward Everett Horton", "Walter Tetley"], "character": [], "site_data": "html Apps Forums Leaderboard Contribute API Support Discover Movies TV Shows Movies Popular Top Rated Upcoming Now Playing TV Shows Popular Top Rated On TV Airing Today People Popular People Can't find a movie or TV show? Login to create it. en Login Sign Up  ID: 27212   Expand The Bullwinkle Show   (1961) User Score Overview We don't have an overview translated in English. Help us expand our database by adding one. Discussions   Reviews Videos   Images   Changes Report Share Discussions General  0 Content Issues  0 Images Backdrops  0 Posters  5 Videos Trailers  0 Teasers  0 Clips  0 Featurettes  0 Opening Credits  0 Top Billed Cast William Conrad Edward Everett Horton Walter Tetley Full Cast & Crew Last Season Season 5 1963 | 14 Episodes Season 5 of The Bullwinkle Show premiered on April  5, 1963. View All Seasons Social Reviews  0 Discussions  0 Media Most Popular Videos  0 Backdrops  0 Posters  5 Recommendations   1966-09-12 The Monkees 6.3    2003-11-07 Dirty Jobs 7.6    1996-09-08 Blue's Clues 6.3    1969-09-26 The Brady Bunch 6.5    1970-09-24 The Odd Couple 7.1    1993-09-13 Late Night with Conan O'Brien 7.3  Facts Status  Ended Networks - Certification  - Type  Scripted Original Language  English Runtime  30m Homepage  - Genres Animation Keywords No keywords have been added. Content Score 36 There's no 'I' in team... Top Contributors M 11 MOvidiu z 4 zurman1 R 2 Rebecca r 1 romangt  View Edit History Popularity Trend  Login to edit  URL By  signing up  for an account on TMDb, you can post directly to Twitter and Facebook. You need to be logged in to continue. Click  here  to login or  here  to sign up.    page_wrap opened in html_head  Join the Community The Basics About TMDb Contact Us Support Forums API Blog Get Involved  Contribution Bible 3rd Party Applications Add New Movie Add New TV Show Community Guidelines Leaderboard Forums Twitter Facebook Legal Terms of Use Privacy Policy Login Sign Up"}